Metadata-Version: 2.4
Name: iflow-mcp_mcp-google-ads
Version: 0.1.0
Summary: Google Ads API integration for Model Context Protocol (MCP)
Author-email: Ernesto Cohnen <ernesto@ixigo.com>
License: MIT
Project-URL: Homepage, https://github.com/cohnen/mcp-google-ads
Project-URL: Bug Tracker, https://github.com/cohnen/mcp-google-ads/issues
Keywords: mcp,google ads,seo,sem,claude,search analytics
Classifier: Development Status :: 4 - Beta
Classifier: Intended Audience :: Developers
Classifier: License :: OSI Approved :: MIT License
Classifier: Programming Language :: Python :: 3
Classifier: Programming Language :: Python :: 3.11
Classifier: Topic :: Internet :: WWW/HTTP :: Indexing/Search
Classifier: Topic :: Software Development :: Libraries :: Python Modules
Requires-Python: >=3.11
License-File: LICENSE
Requires-Dist: google-api-python-client>=2.163.0
Requires-Dist: google-auth-httplib2>=0.2.0
Requires-Dist: google-auth-oauthlib>=1.2.1
Requires-Dist: mcp[cli]>=1.3.0
Requires-Dist: requests>=2.31.0
Requires-Dist: python-dotenv>=1.0.0
Dynamic: license-file
